oceandb_driver_interface/__init__.py
oceandb_driver_interface/constants.py
oceandb_driver_interface/exceptions.py
oceandb_driver_interface/oceandb.py
oceandb_driver_interface/plugin.py
oceandb_driver_interface/search_model.py
oceandb_driver_interface/utils.py
oceandb_driver_interface-0.2.0.dist-info/LICENSE
oceandb_driver_interface-0.2.0.dist-info/METADATA
oceandb_driver_interface-0.2.0.dist-info/WHEEL
oceandb_driver_interface-0.2.0.dist-info/top_level.txt
oceandb_driver_interface-0.2.0.dist-info/RECORD
