Metadata-Version: 2.1
Name: oceandb-driver-interface
Version: 0.2.0
Summary: 🐳 Ocean DB driver interface(Python).
Home-page: https://github.com/oceanprotocol/oceandb-driver-interface
Author: leucothia
Author-email: devops@oceanprotocol.com
License: Apache Software License 2.0
Keywords: oceandb-driver-interface
Platform: UNKNOWN
Classifier: Development Status :: 2 - Pre-Alpha
Classifier: Intended Audience :: Developers
Classifier: License :: OSI Approved :: Apache Software License
Classifier: Natural Language :: English
Classifier: Programming Language :: Python :: 3.4
Classifier: Programming Language :: Python :: 3.5
Classifier: Programming Language :: Python :: 3.6
